biosimulators_utils/__init__.py
biosimulators_utils/__main__.py
biosimulators_utils/_version.py
biosimulators_utils/archive/__init__.py
biosimulators_utils/archive/data_model.py
biosimulators_utils/archive/io.py
biosimulators_utils/archive/utils.py
biosimulators_utils/biosimulations/__init__.py
biosimulators_utils/biosimulations/data_model.py
biosimulators_utils/biosimulations/utils.py
biosimulators_utils/combine/__init__.py
biosimulators_utils/combine/data_model.py
biosimulators_utils/combine/exceptions.py
biosimulators_utils/combine/exec.py
biosimulators_utils/combine/io.py
biosimulators_utils/combine/utils.py
biosimulators_utils/combine/validation.py
biosimulators_utils/config.py
biosimulators_utils/data_model.py
biosimulators_utils/exceptions.py
biosimulators_utils/gh_action/__init__.py
biosimulators_utils/gh_action/core.py
biosimulators_utils/gh_action/data_model.py
biosimulators_utils/globals.py
biosimulators_utils/image.py
biosimulators_utils/kisao/__init__.py
biosimulators_utils/kisao/utils.py
biosimulators_utils/licensing/__init__.py
biosimulators_utils/licensing/core.py
biosimulators_utils/licensing/gurobi.py
biosimulators_utils/log/__init__.py
biosimulators_utils/log/data_model.py
biosimulators_utils/log/utils.py
biosimulators_utils/log/warnings.py
biosimulators_utils/model_lang/__init__.py
biosimulators_utils/model_lang/bngl/__init__.py
biosimulators_utils/model_lang/bngl/utils.py
biosimulators_utils/model_lang/bngl/validation.py
biosimulators_utils/model_lang/cellml/__init__.py
biosimulators_utils/model_lang/cellml/cellml1.0.rnc
biosimulators_utils/model_lang/cellml/cellml1.0.rng
biosimulators_utils/model_lang/cellml/mathml2.rnc
biosimulators_utils/model_lang/cellml/mathml2.rng
biosimulators_utils/model_lang/cellml/utils.py
biosimulators_utils/model_lang/cellml/validation.py
biosimulators_utils/model_lang/lems/__init__.py
biosimulators_utils/model_lang/lems/validation.py
biosimulators_utils/model_lang/neuroml/__init__.py
biosimulators_utils-0.2.3.dist-info/LICENSE
biosimulators_utils-0.2.3.dist-info/METADATA
biosimulators_utils-0.2.3.dist-info/WHEEL
biosimulators_utils-0.2.3.dist-info/entry_points.txt
biosimulators_utils-0.2.3.dist-info/RECORD
