Metadata-Version: 2.1
Name: biosimulators-utils
Version: 0.2.3
Summary: description
Home-page: https://github.com/biosimulators/Biosimulators_utils
License: MIT
Keywords: systems,biology,modeling,simulation
Author: Center for Reproducible Biomedical Modeling
Author-email: info@biosimulators.org
Requires-Python: >=3.10,<4.0
Classifier: Development Status :: 3 - Alpha
Classifier: Intended Audience :: Science/Research
Classifier: License :: OSI Approved :: MIT License
Classifier: Programming Language :: Python :: 3
Classifier: Programming Language :: Python :: 3.10
Classifier: Programming Language :: Python :: 3.11
Classifier: Programming Language :: Python :: 3.12
Classifier: Topic :: Scientific/Engineering :: Bio-Informatics
Provides-Extra: bngl
Provides-Extra: cellml
Provides-Extra: containers
Provides-Extra: escher
Provides-Extra: lems
Provides-Extra: logging
Provides-Extra: neuroml
Provides-Extra: rba
Provides-Extra: sbml
Provides-Extra: simularium
Provides-Extra: smoldyn
Requires-Dist: appdirs
Requires-Dist: bezier ; extra == "escher"
Requires-Dist: bionetgen (>=0.8.4) ; extra == "bngl"
Requires-Dist: biopython
Requires-Dist: capturer ; extra == "logging"
Requires-Dist: cement
Requires-Dist: docker (>=4.4) ; extra == "containers"
Requires-Dist: evalidate (>=2.0)
Requires-Dist: h5py
Requires-Dist: kisao (>=2.33)
Requires-Dist: libcellml (>=0.5.0) ; extra == "cellml"
Requires-Dist: libneuroml ; extra == "neuroml"
Requires-Dist: libroadrunner (>=2.7.0,<3.0.0) ; extra == "bngl"
Requires-Dist: lxml
Requires-Dist: matplotlib
Requires-Dist: mpmath
Requires-Dist: natsort
Requires-Dist: networkx (>=2.6)
Requires-Dist: numpy
Requires-Dist: openpyxl
Requires-Dist: pandas
Requires-Dist: pint ; extra == "lems"
Requires-Dist: pronto (>=2.4)
Requires-Dist: pylems ; extra == "lems"
Requires-Dist: pyneuroml (>=0.5.18) ; extra == "lems" or extra == "neuroml"
Requires-Dist: pyomexmeta (>=1.2.13)
Requires-Dist: python-dateutil
Requires-Dist: python-libcombine (>=0.2.11)
Requires-Dist: python-libsbml ; extra == "sbml"
Requires-Dist: python-libsedml (>=2.0.16)
Requires-Dist: pyyaml
Requires-Dist: rdflib
Requires-Dist: regex
Requires-Dist: requests
Requires-Dist: setuptools (>=74.1.1)
Requires-Dist: simplejson
Requires-Dist: simulariumio ; extra == "simularium"
Requires-Dist: smoldyn (>=2.66) ; extra == "smoldyn"
Requires-Dist: termcolor
Requires-Dist: uritools
Requires-Dist: yamldown
Project-URL: Repository, https://github.com/biosimulators/Biosimulators_utils
